MultiBinary/__init__.py
MultiBinary-1.0.0.dist-info/LICENSE
MultiBinary-1.0.0.dist-info/METADATA
MultiBinary-1.0.0.dist-info/WHEEL
MultiBinary-1.0.0.dist-info/top_level.txt
MultiBinary-1.0.0.dist-info/RECORD
