Metadata-Version: 2.1
Name: MultiBinary
Version: 1.0.0
Summary: A multi-thread binary search
Home-page: https://github.com/Devin-Wallace/MultiBinary
Author: Devin Wallace
Author-email: devinwallace@protonmail.com
License: UNKNOWN
Platform: UNKNOWN
Classifier: Programming Language :: Python :: 3
Classifier: License :: OSI Approved :: MIT License
Classifier: Operating System :: OS Independent
